hiapi/__init__.py
hiapi/hi.py
pyhiapi-0.1.5.dist-info/LICENSE
pyhiapi-0.1.5.dist-info/METADATA
pyhiapi-0.1.5.dist-info/WHEEL
pyhiapi-0.1.5.dist-info/entry_points.txt
pyhiapi-0.1.5.dist-info/top_level.txt
pyhiapi-0.1.5.dist-info/RECORD
