Metadata-Version: 2.1
Name: pyhiapi
Version: 0.1.5
Summary: PyHiAPI - Simple test API
Home-page: https://github.com/ryanjjung/pyhiapi
Author: Ryan Jung
Author-email: ryanjjung@gmail.com
License: LICENCE
Platform: UNKNOWN
Requires-Dist: flask
